simple_tls/__init__.py
simple_tls-0.0.1.dist-info/licenses/LICENSE
simple_tls-0.0.1.dist-info/METADATA
simple_tls-0.0.1.dist-info/WHEEL
simple_tls-0.0.1.dist-info/top_level.txt
simple_tls-0.0.1.dist-info/RECORD
