Metadata-Version: 2.4
Name: simple-tls
Version: 0.0.1
Author: Counter Rain
License: MIT License
Project-URL: Homepage, https://github.com/asphyxiaxx/simple-tls
Project-URL: Bug Tracker, https://github.com/asphyxiaxx/simple-tls/issues
Classifier: Development Status :: 3 - Alpha
Classifier: Intended Audience :: Developers
Classifier: License :: OSI Approved :: MIT License
Classifier: Programming Language :: Python :: 3
Classifier: Topic :: Security :: Cryptography
Classifier: Operating System :: OS Independent
Requires-Python: >=3.7
License-File: LICENSE
Requires-Dist: cryptography>=41.0.0
Dynamic: license-file
